resdk_bcm/__about__.py
resdk_bcm/__init__.py
resdk_bcm/_register.py
resdk_bcm/utils.py
resdk_bcm-1.0.1.dist-info/DESCRIPTION.rst
resdk_bcm-1.0.1.dist-info/METADATA
resdk_bcm-1.0.1.dist-info/RECORD
resdk_bcm-1.0.1.dist-info/WHEEL
resdk_bcm-1.0.1.dist-info/metadata.json
resdk_bcm-1.0.1.dist-info/top_level.txt
