Metadata-Version: 2.0
Name: resdk-bcm
Version: 1.0.1
Summary: BCM Plugin for Resolwe SDK for Python
Home-page: https://github.com/linlabcode/resolwe-bio-py-bcm
Author: UNKNOWN
Author-email: UNKNOWN
License: MIT
Keywords: bioinformatics resolwe bio pipelines dataflow django python sdk
Platform: UNKNOWN
Classifier: Development Status :: 4 - Beta
Classifier: Environment :: Console
Classifier: Intended Audience :: Developers
Classifier: Topic :: Software Development :: Libraries :: Python Modules
Classifier: License :: OSI Approved :: Apache Software License
Classifier: Operating System :: OS Independent
Classifier: Programming Language :: Python
Classifier: Programming Language :: Python :: 2
Classifier: Programming Language :: Python :: 2.7
Classifier: Programming Language :: Python :: 3
Classifier: Programming Language :: Python :: 3.4
Classifier: Programming Language :: Python :: 3.5
Classifier: Programming Language :: Python :: 3.6
Requires-Dist: pexpect (>=4.2.1)
Requires-Dist: resdk (>=1.7.0)
Requires-Dist: six (>=1.10.0)
Provides-Extra: package
Requires-Dist: twine; extra == 'package'
Requires-Dist: wheel; extra == 'package'
Provides-Extra: test
Requires-Dist: check-manifest; extra == 'test'
Requires-Dist: pycodestyle (>=2.1.0); extra == 'test'
Requires-Dist: pydocstyle (>=1.0.0); extra == 'test'
Requires-Dist: pylint (~=1.7.0); extra == 'test'
Requires-Dist: readme-renderer; extra == 'test'
